{"cameraMode":{"drawMode":0,"name":"Shaded","section":"Shading Mode"},"sceneLighting":true,"audioPlay":false,"sceneViewState":{"m_AlwaysRefresh":false,"showFog":true,"showSkybox":true,"showFlares":true,"showImageEffects":true,"showParticleSystems":true,"showVisualEffectGraphs":true,"m_FxEnabled":true},"in2DMode":false,"pivot":{"x":7.699300289154053,"y":15.622281074523926,"z":-15.867719650268555},"rotation":{"x":0.41376152634620669,"y":-0.0671076849102974,"z":0.03060254640877247,"w":0.9074205160140991},"size":10.0,"orthographic":false}